BlackSwanlab/__init__.py
BlackSwanlab/server.py
BlackSwanlab/tracker.py
example_package_Jsqfylune-0.0.1.dist-info/LICENSE
example_package_Jsqfylune-0.0.1.dist-info/METADATA
example_package_Jsqfylune-0.0.1.dist-info/WHEEL
example_package_Jsqfylune-0.0.1.dist-info/top_level.txt
example_package_Jsqfylune-0.0.1.dist-info/RECORD
